LICENSE
README.md
setup.py
bddcli/__init__.py
bddcli/application.py
bddcli/calls.py
bddcli/context.py
bddcli/platform_.py
bddcli/proxy.py
bddcli/runners.py
bddcli.egg-info/PKG-INFO
bddcli.egg-info/SOURCES.txt
bddcli.egg-info/dependency_links.txt
bddcli.egg-info/entry_points.txt
bddcli.egg-info/requires.txt
bddcli.egg-info/top_level.txt
bddcli/authoring/__init__.py
bddcli/authoring/given.py
bddcli/authoring/manipulation.py
bddcli/authoring/story.py
bddcli_bootstrapper/__init__.py