Metadata-Version: 2.1
Name: bddcli
Version: 2.9.0
Summary: Test any command line interface in BDD manner.
Home-page: http://github.com/pylover/bddcli
Author: Vahid Mardani
Author-email: vahid.mardani@gmail.com
License: MIT
Platform: UNKNOWN
Classifier: Environment :: Console
Classifier: Intended Audience :: Developers
Classifier: Natural Language :: English
Classifier: Development Status :: 4 - Beta
Classifier: Development Status :: 5 - Production/Stable
Classifier: License :: OSI Approved :: MIT License
Classifier: Operating System :: OS Independent
Classifier: Programming Language :: Python :: 3.6
Classifier: Topic :: Software Development
